thehelp/__init__.py
thehelp/colormap.py
thehelp/gradient.py
thehelp-0.0.0.dist-info/METADATA
thehelp-0.0.0.dist-info/WHEEL
thehelp-0.0.0.dist-info/licenses/LICENSE.txt
thehelp-0.0.0.dist-info/RECORD
