Metadata-Version: 2.1
Name: thehelp
Version: 0.0.0
Summary: Helpers for use with the rich package.
Project-URL: Homepage, https://github.com/matt-manes/thehelp
Project-URL: Documentation, https://github.com/matt-manes/thehelp/tree/main/docs
Project-URL: Source code, https://github.com/matt-manes/thehelp/tree/main/src/thehelp
Author-email: Matt Manes <mattmanes@pm.me>
License-File: LICENSE.txt
Keywords: rich,shortcuts
Classifier: License :: OSI Approved :: MIT License
Classifier: Operating System :: OS Independent
Classifier: Programming Language :: Python :: 3
Requires-Python: <3.12,>=3.10
Requires-Dist: rich
Requires-Dist: typing-extensions
